README.rst
pyproject.toml
setup.py
nixm/__init__.py
nixm/__main__.py
nixm/client.py
nixm/disk.py
nixm/handler.py
nixm/json.py
nixm/object.py
nixm/store.py
nixm/thread.py
nixm.egg-info/PKG-INFO
nixm.egg-info/SOURCES.txt
nixm.egg-info/dependency_links.txt
nixm.egg-info/entry_points.txt
nixm.egg-info/top_level.txt
nixm/modules/__init__.py
nixm/modules/dbg.py
nixm/modules/err.py
nixm/modules/flt.py
nixm/modules/fnd.py
nixm/modules/irc.py
nixm/modules/llm.py
nixm/modules/log.py
nixm/modules/man.py
nixm/modules/mbx.py
nixm/modules/mdl.py
nixm/modules/mod.py
nixm/modules/req.py
nixm/modules/rss.py
nixm/modules/rst.py
nixm/modules/slg.py
nixm/modules/tbl.py
nixm/modules/tdo.py
nixm/modules/thr.py
nixm/modules/tmr.py
nixm/modules/udp.py
nixm/modules/upt.py
nixm/modules/ver.py
nixm/modules/web.py
nixm/modules/wsd.py