Metadata-Version: 2.1
Name: nixm
Version: 80
Summary: NIXM
Author-email: Bart Thate <bthate@dds.nl>
License: Public Domain
Project-URL: home, https://pypi.org/project/nixm
Project-URL: bugs, https://github.com/otpcr/nixm/issues
Project-URL: source, https://github.com/otpcr/nixm
Classifier: Development Status :: 4 - Beta
Classifier: License :: Public Domain
Classifier: Operating System :: Unix
Classifier: Programming Language :: Python :: 3
Classifier: Topic :: Utilities
